MANIFEST.in
README.md
requirements-dev.txt
requirements.txt
setup.cfg
setup.py
versioneer.py
Examples/Demo_YAML.py
Examples/__init__.py
YODA_Tools.egg-info/PKG-INFO
YODA_Tools.egg-info/SOURCES.txt
YODA_Tools.egg-info/dependency_links.txt
YODA_Tools.egg-info/entry_points.txt
YODA_Tools.egg-info/not-zip-safe
YODA_Tools.egg-info/requires.txt
YODA_Tools.egg-info/top_level.txt
tests/__init__.py
tests/test_util.py
tests/test_converter/__init__.py
tests/test_converter/test_input/__init__.py
tests/test_converter/test_input/test_excel.py
tests/test_converter/test_input/test_yamlInput.py
tests/test_converter/test_output/__init__.py
tests/test_converter/test_output/test_dbOutput.py
tests/test_converter/test_output/test_yamlOutput.py
tests/test_dataloader/__init__.py
tests/test_dataloader/test_ui/__init__.py
yodatools/__init__.py
yodatools/_version.py
yodatools/notebook_test.yaml
yodatools/notebook_test_single.yaml
yodatools/converter/__init__.py
yodatools/converter/main.py
yodatools/converter/Abstract/__init__.py
yodatools/converter/Abstract/iInputs.py
yodatools/converter/Abstract/iOutputs.py
yodatools/converter/Inputs/__init__.py
yodatools/converter/Inputs/excelInput.py
yodatools/converter/Inputs/yamlInput.py
yodatools/converter/Outputs/__init__.py
yodatools/converter/Outputs/dbOutput.py
yodatools/converter/Outputs/yamlOutput.py
yodatools/dataloader/__init__.py
yodatools/dataloader/controller/Main.py
yodatools/dataloader/controller/WizardController.py
yodatools/dataloader/controller/WizardDatabasePageController.py
yodatools/dataloader/controller/WizardExcelPageController.py
yodatools/dataloader/controller/WizardHomePageController.py
yodatools/dataloader/controller/WizardSummaryPageController.py
yodatools/dataloader/controller/WizardYodaPageController.py
yodatools/dataloader/controller/YODA-File.py
yodatools/dataloader/controller/__init__.py
yodatools/dataloader/controller/pnlDBConfig.py
yodatools/dataloader/meta/__init__.py
yodatools/dataloader/meta/data.py
yodatools/dataloader/templates/YODA_SpecimenTimeSeries_Template_0.3-alpha.xlsm
yodatools/dataloader/templates/YODA_TimeSeries_Template_0.3.2-alpha.xlsm
yodatools/dataloader/view/WizardDatabasePageView.py
yodatools/dataloader/view/WizardExcelPageView.py
