Metadata-Version: 1.1
Name: YODA-Tools
Version: 0.2.0a0
Summary: Tools to validate and manage YODA files
Home-page: UNKNOWN
Author: Stephanie Reeder
Author-email: stephanie.reeder@usu.edu
License: UNKNOWN
Platform: any
Classifier: Development Status :: 3 - Alpha
Classifier: Intended Audience :: Science/Research
Classifier: License :: OSI Approved :: BSD License
Classifier: Operating System :: OS Independent
Classifier: Programming Language :: Python
Classifier: Programming Language :: Python :: 2.7
Classifier: Programming Language :: Python :: 3.4
Classifier: Programming Language :: Python :: 3.5
Classifier: Programming Language :: Python :: 3.6
Classifier: Topic :: Software Development :: Libraries :: Python Modules
